README.md
setup.py
conda_press/__init__.py
conda_press/__main__.py
conda_press/condatools.xsh
conda_press/config.py
conda_press/main.xsh
conda_press/wheel.xsh
conda_press.egg-info/PKG-INFO
conda_press.egg-info/SOURCES.txt
conda_press.egg-info/dependency_links.txt
conda_press.egg-info/not-zip-safe
conda_press.egg-info/requires.txt
conda_press.egg-info/top_level.txt
scripts/conda-press