Metadata-Version: 2.1
Name: conda-press
Version: 0.0.6
Summary: Press conda packages into wheels
Home-page: https://github.com/regro/conda-press
Author: Anthony Scopatz
Author-email: scopatz@gmail.com
Maintainer: Anthony Scopatz
License: BSD
Platform: Cross Platform
Classifier: Programming Language :: Python :: 3
Requires-Python: >=3.6
